2x1_mux/design.sv
// Code your design here
`timescale 1ns/1ps
module mux_2x1(s,in,out);
  input s;
  input[1:0] in;
  output reg out;
  always @(*)
  casex(s)
    1'b0:begin out=in[0]; end
    1'b1:begin out=in[1];end
    default:out=1'bx;
  endcase
endmodule

2x1_mux/testbench.sv
// Code your testbench here
// or browse Examples
`timescale 1ns/1ps
module tb_mux_2x1();
  reg s;
  reg [1:0]in;
  wire out;
  integer i;
  mux_2x1 uut(
    .s(s),.in(in),.out(out));
  initial
    begin
      s=0;
      in=2'b00;
    $dumpfile("tb_mux_2x1.vcd");
    $dumpvars(0, uut);
    end
//   initial
//     begin
//      for (i=0; i<8; i=i+1) begin
//        {s,in} = i;
//     #2;
//   end
//     end
  always #4 s=s+1;
  always #1 in=in+1;
  initial 
    begin
      $monitor("time=%g,s=%b,a=%b,b=%b,out=%b",$time,s,in[1],in[0],out);
  #16 $finish;
    end
endmodule

2x1_mux/tb_mux_2x1.vcd
$date
	Fri Aug 22 12:39:22 2025
$end
$version
	Icarus Verilog
$end
$timescale
	1ps
$end
$scope module tb_mux_2x1 $end
$scope module uut $end
$var wire 2 ! in [1:0] $end
$var wire 1 " s $end
$var reg 1 # out $end
$upscope $end
$upscope $end
$enddefinitions $end
$comment Show the parameter values. $end
$dumpall
$end
#0
$dumpvars
0#
0"
b0 !
$end
#1000
1#
b1 !
#2000
0#
b10 !
#3000
1#
b11 !
#4000
0#
b0 !
1"
#5000
b1 !
#6000
1#
b10 !
#7000
b11 !
#8000
0#
b0 !
0"
#9000
1#
b1 !
#10000
0#
b10 !
#11000
1#
b11 !
#12000
0#
b0 !
1"
#13000
b1 !
#14000
1#
b10 !
#15000
b11 !
#16000
0#
b0 !
0"
