d_flipflop/design.sv
`timescale 1ns/1ps
module dff(output reg q,qbar,input d,clk,clear);
  always @ (posedge clk or negedge clear)
    if(clear==1'b0)
      begin
        q<=1'b0;
        qbar<=1'b1;
      end
  else 
    begin
      q<=d;
      qbar<=~d;
    end
endmodule

d_flipflop/testbench.sv
`timescale 1ns/1ps
module tb_dff;
  reg d,clk,clear;
  wire q,qbar;
  
  dff uut(.q(q),.qbar(qbar),.d(d),.clk(clk),.clear(clear));
  
  initial
    begin
      clk=1'b0;
      forever #5 clk=~clk;
    end
  initial
    begin
      d=1'b0;
      clear=1'b1;
       clear = 1'b0;    // start with reset active
    #5 clear = 1'b1; // release reset before first posedge clk
      $dumpfile("tb_dff.vcd");
    	$dumpvars(0, uut);
    end
  always #2 d=~d;
  initial
    begin
      $monitor("time=%g,d=%b,clk=%b,clear=%b,q=%b,qbar=%b",$time,d,clk,clear,q,qbar);
  #100 $finish;
    end
endmodule

d_flipflop/tb_dff.vcd
$date
	Thu Aug 21 17:11:43 2025
$end
$version
	Icarus Verilog
$end
$timescale
	1ps
$end
$scope module tb_dff $end
$scope module uut $end
$var wire 1 ! clear $end
$var wire 1 " clk $end
$var wire 1 # d $end
$var reg 1 $ q $end
$var reg 1 % qbar $end
$upscope $end
$upscope $end
$enddefinitions $end
$comment Show the parameter values. $end
$dumpall
$end
#5000
$dumpvars
1%
0$
0#
1"
1!
$end
#6000
1#
#8000
0#
#10000
1#
0"
#12000
0#
#14000
1#
#15000
0%
1$
1"
#16000
0#
#18000
1#
#20000
0#
0"
#22000
1#
#24000
0#
#25000
1%
0$
1"
#26000
1#
#28000
0#
#30000
1#
0"
#32000
0#
#34000
1#
#35000
0%
1$
1"
#36000
0#
#38000
1#
#40000
0#
0"
#42000
1#
#44000
0#
#45000
1%
0$
1"
#46000
1#
#48000
0#
#50000
1#
0"
#52000
0#
#54000
1#
#55000
0%
1$
1"
#56000
0#
#58000
1#
#60000
0#
0"
#62000
1#
#64000
0#
#65000
1%
0$
1"
#66000
1#
#68000
0#
#70000
1#
0"
#72000
0#
#74000
1#
#75000
0%
1$
1"
#76000
0#
#78000
1#
#80000
0#
0"
#82000
1#
#84000
0#
#85000
1%
0$
1"
#86000
1#
#88000
0#
#90000
1#
0"
#92000
0#
#94000
1#
#95000
0%
1$
1"
#96000
0#
#98000
1#
#100000
0#
0"
