sr_flipflop/design.sv
`timescale 1ns/1ps
module sr_ff(output reg q,qbar,input s,r,clk,clear);
  always @ (posedge clk  or negedge clear)
    if(!clear)
      begin
        q<=1'b0;
        qbar<=1'b1;
      end
  else 
    begin
      casex({s,r})
      2'b00:begin q<=q;qbar<=qbar; end
      2'b01:begin q<=1'b0;qbar<=1'b1; end
      2'b10:begin q<=1'b1;qbar<=1'b0; end
      default: {q,qbar} <= 2'bxx;
    endcase
    end
endmodule

sr_flipflop/testbench.sv
`timescale 1ns/1ps
module tb_sr_ff;
  reg s,r,clk,clear;
  reg q,qbar;
  
  sr_ff uut(.s(s),.r(r),.qbar(qbar),.q(q),.clk(clk),.clear(clear));
  
  initial
    begin
      clk=1'b0;
      forever #5 clk=~clk;
    end
  initial
    begin
      s=1'b0;
      r=1'b0;
       clear = 1'b0;    // start with reset active
    #5 clear = 1'b1; // release reset before first posedge clk
      $dumpfile("tb_sr_ff.vcd");
    	$dumpvars(0, uut);
    end
  always #10 s=~s;
  always #15 r=~r;
  initial
    begin
      $monitor("time=%g,s=%b,r=%b,clk=%b,clear=%b,q=%b,qbar=%b",$time,s,r,clk,clear,q,qbar);
  #100 $finish;
    end
endmodule

sr_flipflop/tb_sr_ff.vcd
$date
	Thu Aug 21 17:46:31 2025
$end
$version
	Icarus Verilog
$end
$timescale
	1ps
$end
$scope module tb_sr_ff $end
$scope module uut $end
$var wire 1 ! clear $end
$var wire 1 " clk $end
$var wire 1 # r $end
$var wire 1 $ s $end
$var reg 1 % q $end
$var reg 1 & qbar $end
$upscope $end
$upscope $end
$enddefinitions $end
$comment Show the parameter values. $end
$dumpall
$end
#5000
$dumpvars
1&
0%
0$
0#
1"
1!
$end
#10000
0"
1$
#15000
x%
x&
1"
1#
#20000
0"
0$
#25000
1&
0%
1"
#30000
0"
1$
0#
#35000
0&
1%
1"
#40000
0"
0$
#45000
1&
0%
1"
1#
#50000
0"
1$
#55000
x%
x&
1"
#60000
0"
0$
0#
#65000
1"
#70000
0"
1$
#75000
1"
1#
#80000
0"
0$
#85000
1&
0%
1"
#90000
0"
1$
0#
#95000
0&
1%
1"
#100000
0"
0$
