demux_1x8/design.sv
// Code your design here
`timescale 1ns/1ps

module demux_1x8(s,in,out);
  output [7:0]out;
  input in;
  input [2:0] s;
  wire [5:0]k;
  demux_1x2 m0(s[2],in,k[1:0]);
  demux_1x2 m1(s[1],k[1],k[5:4]);
  demux_1x2 m2(s[1],k[0],k[3:2]);
  demux_1x2 m3(s[0],k[5],out[7:6]);
  demux_1x2 m4(s[0],k[4],out[5:4]);
  demux_1x2 m5(s[0],k[3],out[3:2]);
  demux_1x2 m6(s[0],k[2], out[1:0]);
endmodule

module demux_1x2(s,in,out);
  input s;
  input in;
  output reg [1:0]out;
  always @(*)
  casex(s)
    1'b0:begin out[0]=in;out[1]=1'b0;end
    1'b1:begin out[1]=in;out[0]=1'b0;end
    default:out=2'bxx;
  endcase
endmodule

demux_1x8/testbench.sv
// Code your testbench here
// or browse Examples
`timescale 1ns/1ps
module tb_demux_1x8();
  reg  [2:0] s;
  reg in;
  wire [7:0] out;
  integer i,j;
  demux_1x8 uut(
    .s(s),.in(in),.out(out));
  initial
    begin
      s=3'b000;
      in=1'b0;
      $dumpfile("tb_demux_1x8.vcd");
    $dumpvars(0, uut);
    end
  initial begin
    for (i = 0; i <8; i = i + 1) begin
      s = i;
      for (j = 0; j <= 1; j = j + 1) begin
        in = j;
        #2;
      end
    end
  end
  initial 
    begin
      $monitor("time=%g,s=%b,in=%b,out=%b",$time,s,in,out);
  #32 $finish;
    end
endmodule

demux_1x8/tb_demux_1x8.vcd
$date
	Fri Aug 22 15:19:17 2025
$end
$version
	Icarus Verilog
$end
$timescale
	1ps
$end
$scope module tb_demux_1x8 $end
$scope module uut $end
$var wire 1 ! in $end
$var wire 3 " s [2:0] $end
$var wire 8 # out [7:0] $end
$var wire 6 $ k [5:0] $end
$scope module m0 $end
$var wire 1 ! in $end
$var wire 1 % s $end
$var reg 2 & out [1:0] $end
$upscope $end
$scope module m1 $end
$var wire 1 ' in $end
$var wire 1 ( s $end
$var reg 2 ) out [1:0] $end
$upscope $end
$scope module m2 $end
$var wire 1 * in $end
$var wire 1 + s $end
$var reg 2 , out [1:0] $end
$upscope $end
$scope module m3 $end
$var wire 1 - in $end
$var wire 1 . s $end
$var reg 2 / out [1:0] $end
$upscope $end
$scope module m4 $end
$var wire 1 0 in $end
$var wire 1 1 s $end
$var reg 2 2 out [1:0] $end
$upscope $end
$scope module m5 $end
$var wire 1 3 in $end
$var wire 1 4 s $end
$var reg 2 5 out [1:0] $end
$upscope $end
$scope module m6 $end
$var wire 1 6 in $end
$var wire 1 7 s $end
$var reg 2 8 out [1:0] $end
$upscope $end
$upscope $end
$upscope $end
$enddefinitions $end
$comment Show the parameter values. $end
$dumpall
$end
#0
$dumpvars
b0 8
07
06
b0 5
04
03
b0 2
01
00
b0 /
0.
0-
b0 ,
0+
0*
b0 )
0(
0'
b0 &
0%
b0 $
b0 #
b0 "
0!
$end
#2000
b1 #
b1 8
16
b1 ,
1*
b101 $
b1 &
1!
#4000
06
b0 ,
0*
b0 #
b0 8
b0 $
b0 &
1.
11
14
17
0!
b1 "
#6000
b10 #
b10 8
16
b1 ,
1*
b101 $
b1 &
1!
#8000
b0 5
06
03
0*
b0 ,
b0 #
b0 8
b0 $
b0 &
1(
1+
0.
01
04
07
0!
b10 "
#10000
b100 #
b1 5
13
b10 ,
1*
b1001 $
b1 &
1!
#12000
03
b0 ,
0*
b0 #
b0 5
b0 $
b0 &
1.
11
14
17
0!
b11 "
#14000
b1000 #
b10 5
13
b10 ,
1*
b1001 $
b1 &
1!
#16000
b0 8
03
06
0*
b0 ,
b0 #
b0 5
b0 $
b0 &
1%
0(
0+
0.
01
04
07
0!
b100 "
#18000
b10000 #
b1 2
10
b1 )
1'
b10010 $
b10 &
1!
#20000
00
b0 )
0'
b0 #
b0 2
b0 $
b0 &
1.
11
14
17
0!
b101 "
#22000
b100000 #
b10 2
10
b1 )
1'
b10010 $
b10 &
1!
#24000
b0 /
00
0-
0'
b0 )
b0 #
b0 2
b0 $
b0 &
1(
1+
0.
01
04
07
0!
b110 "
#26000
b1000000 #
b1 /
1-
b10 )
1'
b100010 $
b10 &
1!
#28000
0-
b0 )
0'
b0 #
b0 /
b0 $
b0 &
1.
11
14
17
0!
b111 "
#30000
b10000000 #
b10 /
1-
b10 )
1'
b100010 $
b10 &
1!
