mod_3_to_12_up_down_counter_with_load/design.sv
`timescale 1ns/1ps
module up_down_counter_3to12(
    input clk,
    input reset,       // synchronous active-high reset
    input up_down,     // 1 = up, 0 = down
    input load,        // synchronous load enable
    input [3:0] d,     // parallel load value
    output reg [3:0] q
);

    always @(posedge clk) begin
        if (reset)
            q <= 4'd3;  // start from 3
        else if (load)
            q <= d;
        else if (up_down) begin
            if (q == 4'd12)
                q <= 4'd3;
            else
                q <= q + 1;
        end else begin
            if (q == 4'd3)
                q <= 4'd12;
            else
                q <= q - 1;
        end
    end

endmodule

mod_3_to_12_up_down_counter_with_load/testbench.sv
`timescale 1ns/1ps
module tb_up_down_counter_3to12();

  reg clk;
  reg reset;
  reg up_down;
  reg load;
  reg [3:0] d;
  wire [3:0] q;

  up_down_counter_3to12 uut (
    .clk(clk),
    .reset(reset),
    .up_down(up_down),
    .load(load),
    .d(d),
    .q(q)
  );

  initial begin
    clk = 0;
    forever #5 clk = ~clk;
  end

  initial begin
    $dumpfile("tb_up_down_counter_3to12.vcd");
    $dumpvars(0, uut);
  end

  initial begin
    reset = 1; load = 0; up_down = 1; d = 4'd0;
    #10 reset = 0;

    up_down = 1;
    #100;

    up_down = 0;
    #100;

    load = 1; d = 4'd7;
    #10 load = 0;
    up_down = 1;
    #50;

    $finish;
  end

  initial begin
    $monitor("time=%0t | reset=%b | load=%b | up_down=%b | q=%d",
             $time, reset, load, up_down, q);
  end

endmodule

mod_3_to_12_up_down_counter_with_load/tb_up_down_counter_3to12.vcd
$date
	Fri Aug 22 17:15:20 2025
$end
$version
	Icarus Verilog
$end
$timescale
	1ps
$end
$scope module tb_up_down_counter_3to12 $end
$scope module uut $end
$var wire 1 ! clk $end
$var wire 4 " d [3:0] $end
$var wire 1 # load $end
$var wire 1 $ reset $end
$var wire 1 % up_down $end
$var reg 4 & q [3:0] $end
$upscope $end
$upscope $end
$enddefinitions $end
$comment Show the parameter values. $end
$dumpall
$end
#0
$dumpvars
bx &
1%
1$
0#
b0 "
0!
$end
#5000
b11 &
1!
#10000
0!
0$
#15000
b100 &
1!
#20000
0!
#25000
b101 &
1!
#30000
0!
#35000
b110 &
1!
#40000
0!
#45000
b111 &
1!
#50000
0!
#55000
b1000 &
1!
#60000
0!
#65000
b1001 &
1!
#70000
0!
#75000
b1010 &
1!
#80000
0!
#85000
b1011 &
1!
#90000
0!
#95000
b1100 &
1!
#100000
0!
#105000
b11 &
1!
#110000
0!
0%
#115000
b1100 &
1!
#120000
0!
#125000
b1011 &
1!
#130000
0!
#135000
b1010 &
1!
#140000
0!
#145000
b1001 &
1!
#150000
0!
#155000
b1000 &
1!
#160000
0!
#165000
b111 &
1!
#170000
0!
#175000
b110 &
1!
#180000
0!
#185000
b101 &
1!
#190000
0!
#195000
b100 &
1!
#200000
0!
#205000
b11 &
1!
#210000
0!
b111 "
1#
#215000
b111 &
1!
#220000
0!
1%
0#
#225000
b1000 &
1!
#230000
0!
#235000
b1001 &
1!
#240000
0!
#245000
b1010 &
1!
#250000
0!
#255000
b1011 &
1!
#260000
0!
#265000
b1100 &
1!
