siso/design.sv
`timescale 1ns/1ps
module siso_right(
  input clk, rst, d,
  output reg [3:0] q
);
  always @(posedge clk or posedge rst) begin
    if (rst)
      q <= 4'b0000;
    else
      q <= {d, q[3:1]};
  end
endmodule

siso/testbench.sv
`timescale 1ns/1ps
module tb_siso_right;
  reg clk, rst, d;
  wire [3:0] q;

  siso_right uut (.clk(clk), .rst(rst), .d(d), .q(q));

  initial clk = 0;
  always #5 clk = ~clk;

  initial begin
    $dumpfile("tb_siso_right.vcd");
    $dumpvars(0, uut);
  end

  initial begin
    rst = 1; d = 0;
    #10 rst = 0; d = 1;
    #10 d = 0;
    #10 d = 1;
    #10 d = 1;
    #20 $finish;
  end

  initial begin
    $monitor("time=%0t | d=%b | q=%b", $time, d, q);
  end
endmodule

siso/tb_siso_right.vcd
$date
	Fri Aug 22 16:55:01 2025
$end
$version
	Icarus Verilog
$end
$timescale
	1ps
$end
$scope module tb_siso_right $end
$scope module uut $end
$var wire 1 ! clk $end
$var wire 1 " d $end
$var wire 1 # rst $end
$var reg 4 $ q [3:0] $end
$upscope $end
$upscope $end
$enddefinitions $end
$comment Show the parameter values. $end
$dumpall
$end
#0
$dumpvars
b0 $
1#
0"
0!
$end
#5000
1!
#10000
0!
1"
0#
#15000
b1000 $
1!
#20000
0!
0"
#25000
b100 $
1!
#30000
0!
1"
#35000
b1010 $
1!
#40000
0!
#45000
b1101 $
1!
#50000
0!
#55000
b1110 $
1!
