3x8_decoder/design.sv
`timescale 1ns/1ps
module decoder_3x8 (
  input  [2:0] in,
  output reg [7:0] out
);

  always @(*) begin
    case (in)
      3'b000: out = 8'b00000001;
      3'b001: out = 8'b00000010;
      3'b010: out = 8'b00000100;
      3'b011: out = 8'b00001000;
      3'b100: out = 8'b00010000;
      3'b101: out = 8'b00100000;
      3'b110: out = 8'b01000000;
      3'b111: out = 8'b10000000;
      default: out = 8'b00000000;
    endcase
  end

endmodule

3x8_decoder/testbench.sv
`timescale 1ns/1ps
module tb_decoder_3x8();

  reg  [2:0] in;
  wire [7:0] out;
  integer i;

  decoder_3x8 uut (.in(in), .out(out));

  initial begin
    $dumpfile("tb_decoder_3x8.vcd");
    $dumpvars(0, uut);
  end

  initial begin
    for (i = 0; i < 8; i = i + 1) begin
      in = i;
      #2;
    end
  end

  initial begin
    $monitor("time=%g | in=%b | out=%b", $time, in, out);
    #20 $finish;
  end

endmodule

3x8_decoder/tb_decoder_3x8.vcd
$date
	Fri Aug 22 15:37:09 2025
$end
$version
	Icarus Verilog
$end
$timescale
	1ps
$end
$scope module tb_decoder_3x8 $end
$scope module uut $end
$var wire 3 ! in [2:0] $end
$var reg 8 " out [7:0] $end
$upscope $end
$upscope $end
$enddefinitions $end
$comment Show the parameter values. $end
$dumpall
$end
#0
$dumpvars
b1 "
b0 !
$end
#2000
b10 "
b1 !
#4000
b100 "
b10 !
#6000
b1000 "
b11 !
#8000
b10000 "
b100 !
#10000
b100000 "
b101 !
#12000
b1000000 "
b110 !
#14000
b10000000 "
b111 !
