8x1_mux/design.sv
// Code your design here
`timescale 1ns/1ps
module mux_8x1(s,in,out);
  output out;
  input [7:0]in;
  input [2:0] s;
  wire [5:0]k;
  mux_2x1 m0(s[0],in[1:0],k[0]);
  mux_2x1 m1(s[0],in[3:2],k[1]);
  mux_2x1 m2(s[0],in[5:4],k[2]);
  mux_2x1 m3(s[0],in[7:6],k[3]);
mux_2x1 m4(s[1], {k[1],k[0]}, k[4]);
mux_2x1 m5(s[1], {k[3],k[2]}, k[5]);
mux_2x1 m6(s[2], {k[5],k[4]}, out);
endmodule



module mux_2x1(s,in,out);
  input s;
  input[1:0] in;
  output reg out;
  always @(*)
  casex(s)
    1'b0:begin out=in[0]; end
    1'b1:begin out=in[1];end
    default:out=1'bx;
  endcase
endmodule

8x1_mux/testbench.sv
// Code your testbench here
// or browse Examples
`timescale 1ns/1ps
module tb_mux_8x1();
  reg [2:0]s;
  reg [7:0]in;
  wire out;
  integer i,j;
  mux_8x1 uut(
    .s(s),.in(in),.out(out));
  initial
    begin
      s=3'b000;
      in=8'b00000000;
      $dumpfile("tb_mux_8x1.vcd");
    $dumpvars(0, uut);
    end
  initial begin
    for (i = 0; i < 8; i = i + 1) begin
      s = i;
      for (j = 0; j < 256; j = j + 1) begin
        in = j;
        #2;
      end
    end
  end
  initial 
    begin
      $monitor("time=%g,s=%b,in=%b,out=%b",$time,s,in,out);
  #5000 $finish;
    end
endmodule

8x1_mux/tb_mux_8x1.vcd
$date
	Fri Aug 22 13:00:20 2025
$end
$version
	Icarus Verilog
$end
$timescale
	1ps
$end
$scope module tb_mux_8x1 $end
$scope module uut $end
$var wire 8 ! in [7:0] $end
$var wire 3 " s [2:0] $end
$var wire 1 # out $end
$var wire 6 $ k [5:0] $end
$scope module m0 $end
$var wire 2 % in [1:0] $end
$var wire 1 & s $end
$var reg 1 ' out $end
$upscope $end
$scope module m1 $end
$var wire 2 ( in [1:0] $end
$var wire 1 ) s $end
$var reg 1 * out $end
$upscope $end
$scope module m2 $end
$var wire 2 + in [1:0] $end
$var wire 1 , s $end
$var reg 1 - out $end
$upscope $end
$scope module m3 $end
$var wire 2 . in [1:0] $end
$var wire 1 / s $end
$var reg 1 0 out $end
$upscope $end
$scope module m4 $end
$var wire 2 1 in [1:0] $end
$var wire 1 2 s $end
$var reg 1 3 out $end
$upscope $end
$scope module m5 $end
$var wire 2 4 in [1:0] $end
$var wire 1 5 s $end
$var reg 1 6 out $end
$upscope $end
$scope module m6 $end
$var wire 2 7 in [1:0] $end
$var wire 1 8 s $end
$var reg 1 # out $end
$upscope $end
$upscope $end
$upscope $end
$enddefinitions $end
$comment Show the parameter values. $end
$dumpall
$end
#0
$dumpvars
08
b0 7
06
05
b0 4
03
02
b0 1
00
0/
b0 .
0-
0,
b0 +
0*
0)
b0 (
0'
0&
b0 %
b0 $
0#
b0 "
b0 !
$end
#2000
1#
b1 7
13
b1 1
b10001 $
1'
b1 %
b1 !
#4000
0#
b0 7
03
b0 1
b0 $
0'
b10 %
b10 !
#6000
1#
b1 7
13
b1 1
b10001 $
1'
b11 %
b11 !
#8000
0#
b0 7
03
b10 1
0'
b10 $
1*
b0 %
b1 (
b100 !
#10000
1#
b1 7
13
b11 1
b10011 $
1'
b1 %
b101 !
#12000
0#
b0 7
03
b10 1
b10 $
0'
b10 %
b110 !
#14000
1#
b1 7
13
b11 1
b10011 $
1'
b11 %
b111 !
#16000
0#
b0 7
03
b0 1
0'
b0 $
0*
b0 %
b10 (
b1000 !
#18000
1#
b1 7
13
b1 1
b10001 $
1'
b1 %
b1001 !
#20000
0#
b0 7
03
b0 1
b0 $
0'
b10 %
b1010 !
#22000
1#
b1 7
13
b1 1
b10001 $
1'
b11 %
b1011 !
#24000
0#
b0 7
03
b10 1
0'
b10 $
1*
b0 %
b11 (
b1100 !
#26000
1#
b1 7
13
b11 1
b10011 $
1'
b1 %
b1101 !
#28000
0#
b0 7
03
b10 1
b10 $
0'
b10 %
b1110 !
#30000
1#
b1 7
13
b11 1
b10011 $
1'
b11 %
b1111 !
#32000
0#
b10 7
03
16
b0 1
b1 4
0'
0*
b100100 $
1-
b0 %
b0 (
b1 +
b10000 !
#34000
1#
b11 7
13
b1 1
b110101 $
1'
b1 %
b10001 !
#36000
0#
b10 7
03
b0 1
b100100 $
0'
b10 %
b10010 !
#38000
1#
b11 7
13
b1 1
b110101 $
1'
b11 %
b10011 !
#40000
0#
b10 7
03
b10 1
0'
b100110 $
1*
b0 %
b1 (
b10100 !
#42000
1#
b11 7
13
b11 1
b110111 $
1'
b1 %
b10101 !
#44000
0#
b10 7
03
b10 1
b100110 $
0'
b10 %
b10110 !
#46000
1#
b11 7
13
b11 1
b110111 $
1'
b11 %
b10111 !
#48000
0#
b10 7
03
b0 1
0'
b100100 $
0*
b0 %
b10 (
b11000 !
#50000
1#
b11 7
13
b1 1
b110101 $
1'
b1 %
b11001 !
#52000
0#
b10 7
03
b0 1
b100100 $
0'
b10 %
b11010 !
#54000
1#
b11 7
13
b1 1
b110101 $
1'
b11 %
b11011 !
#56000
0#
b10 7
03
b10 1
0'
b100110 $
1*
b0 %
b11 (
b11100 !
#58000
1#
b11 7
13
b11 1
b110111 $
1'
b1 %
b11101 !
#60000
0#
b10 7
03
b10 1
b100110 $
0'
b10 %
b11110 !
#62000
1#
b11 7
13
b11 1
b110111 $
1'
b11 %
b11111 !
#64000
0#
b0 7
03
06
b0 1
b0 4
0'
0*
b0 $
0-
b0 %
b0 (
b10 +
b100000 !
#66000
1#
b1 7
13
b1 1
b10001 $
1'
b1 %
b100001 !
#68000
0#
b0 7
03
b0 1
b0 $
0'
b10 %
b100010 !
#70000
1#
b1 7
13
b1 1
b10001 $
1'
b11 %
b100011 !
#72000
0#
b0 7
03
b10 1
0'
b10 $
1*
b0 %
b1 (
b100100 !
#74000
1#
b1 7
13
b11 1
b10011 $
1'
b1 %
b100101 !
#76000
0#
b0 7
03
b10 1
b10 $
0'
b10 %
b100110 !
#78000
1#
b1 7
13
b11 1
b10011 $
1'
b11 %
b100111 !
#80000
0#
b0 7
03
b0 1
0'
b0 $
0*
b0 %
b10 (
b101000 !
#82000
1#
b1 7
13
b1 1
b10001 $
1'
b1 %
b101001 !
#84000
0#
b0 7
03
b0 1
b0 $
0'
b10 %
b101010 !
#86000
1#
b1 7
13
b1 1
b10001 $
1'
b11 %
b101011 !
#88000
0#
b0 7
03
b10 1
0'
b10 $
1*
b0 %
b11 (
b101100 !
#90000
1#
b1 7
13
b11 1
b10011 $
1'
b1 %
b101101 !
#92000
0#
b0 7
03
b10 1
b10 $
0'
b10 %
b101110 !
#94000
1#
b1 7
13
b11 1
b10011 $
1'
b11 %
b101111 !
#96000
0#
b10 7
03
16
b0 1
b1 4
0'
0*
b100100 $
1-
b0 %
b0 (
b11 +
b110000 !
#98000
1#
b11 7
13
b1 1
b110101 $
1'
b1 %
b110001 !
#100000
0#
b10 7
03
b0 1
b100100 $
0'
b10 %
b110010 !
#102000
1#
b11 7
13
b1 1
b110101 $
1'
b11 %
b110011 !
#104000
0#
b10 7
03
b10 1
0'
b100110 $
1*
b0 %
b1 (
b110100 !
#106000
1#
b11 7
13
b11 1
b110111 $
1'
b1 %
b110101 !
#108000
0#
b10 7
03
b10 1
b100110 $
0'
b10 %
b110110 !
#110000
1#
b11 7
13
b11 1
b110111 $
1'
b11 %
b110111 !
#112000
0#
b10 7
03
b0 1
0'
b100100 $
0*
b0 %
b10 (
b111000 !
#114000
1#
b11 7
13
b1 1
b110101 $
1'
b1 %
b111001 !
#116000
0#
b10 7
03
b0 1
b100100 $
0'
b10 %
b111010 !
#118000
1#
b11 7
13
b1 1
b110101 $
1'
b11 %
b111011 !
#120000
0#
b10 7
03
b10 1
0'
b100110 $
1*
b0 %
b11 (
b111100 !
#122000
1#
b11 7
13
b11 1
b110111 $
1'
b1 %
b111101 !
#124000
0#
b10 7
03
b10 1
b100110 $
0'
b10 %
b111110 !
#126000
1#
b11 7
13
b11 1
b110111 $
1'
b11 %
b111111 !
#128000
0#
b0 7
03
06
b0 1
b10 4
0'
0*
0-
b1000 $
10
b0 %
b0 (
b0 +
b1 .
b1000000 !
#130000
1#
b1 7
13
b1 1
b11001 $
1'
b1 %
b1000001 !
#132000
0#
b0 7
03
b0 1
b1000 $
0'
b10 %
b1000010 !
#134000
1#
b1 7
13
b1 1
b11001 $
1'
b11 %
b1000011 !
#136000
0#
b0 7
03
b10 1
0'
b1010 $
1*
b0 %
b1 (
b1000100 !
#138000
1#
b1 7
13
b11 1
b11011 $
1'
b1 %
b1000101 !
#140000
0#
b0 7
03
b10 1
b1010 $
0'
b10 %
b1000110 !
#142000
1#
b1 7
13
b11 1
b11011 $
1'
b11 %
b1000111 !
#144000
0#
b0 7
03
b0 1
0'
b1000 $
0*
b0 %
b10 (
b1001000 !
#146000
1#
b1 7
13
b1 1
b11001 $
1'
b1 %
b1001001 !
#148000
0#
b0 7
03
b0 1
b1000 $
0'
b10 %
b1001010 !
#150000
1#
b1 7
13
b1 1
b11001 $
1'
b11 %
b1001011 !
#152000
0#
b0 7
03
b10 1
0'
b1010 $
1*
b0 %
b11 (
b1001100 !
#154000
1#
b1 7
13
b11 1
b11011 $
1'
b1 %
b1001101 !
#156000
0#
b0 7
03
b10 1
b1010 $
0'
b10 %
b1001110 !
#158000
1#
b1 7
13
b11 1
b11011 $
1'
b11 %
b1001111 !
#160000
0#
b10 7
03
16
b0 1
b11 4
0'
0*
b101100 $
1-
b0 %
b0 (
b1 +
b1010000 !
#162000
1#
b11 7
13
b1 1
b111101 $
1'
b1 %
b1010001 !
#164000
0#
b10 7
03
b0 1
b101100 $
0'
b10 %
b1010010 !
#166000
1#
b11 7
13
b1 1
b111101 $
1'
b11 %
b1010011 !
#168000
0#
b10 7
03
b10 1
0'
b101110 $
1*
b0 %
b1 (
b1010100 !
#170000
1#
b11 7
13
b11 1
b111111 $
1'
b1 %
b1010101 !
#172000
0#
b10 7
03
b10 1
b101110 $
0'
b10 %
b1010110 !
#174000
1#
b11 7
13
b11 1
b111111 $
1'
b11 %
b1010111 !
#176000
0#
b10 7
03
b0 1
0'
b101100 $
0*
b0 %
b10 (
b1011000 !
#178000
1#
b11 7
13
b1 1
b111101 $
1'
b1 %
b1011001 !
#180000
0#
b10 7
03
b0 1
b101100 $
0'
b10 %
b1011010 !
#182000
1#
b11 7
13
b1 1
b111101 $
1'
b11 %
b1011011 !
#184000
0#
b10 7
03
b10 1
0'
b101110 $
1*
b0 %
b11 (
b1011100 !
#186000
1#
b11 7
13
b11 1
b111111 $
1'
b1 %
b1011101 !
#188000
0#
b10 7
03
b10 1
b101110 $
0'
b10 %
b1011110 !
#190000
1#
b11 7
13
b11 1
b111111 $
1'
b11 %
b1011111 !
#192000
0#
b0 7
03
06
b0 1
b10 4
0'
0*
b1000 $
0-
b0 %
b0 (
b10 +
b1100000 !
#194000
1#
b1 7
13
b1 1
b11001 $
1'
b1 %
b1100001 !
#196000
0#
b0 7
03
b0 1
b1000 $
0'
b10 %
b1100010 !
#198000
1#
b1 7
13
b1 1
b11001 $
1'
b11 %
b1100011 !
#200000
0#
b0 7
03
b10 1
0'
b1010 $
1*
b0 %
b1 (
b1100100 !
#202000
1#
b1 7
13
b11 1
b11011 $
1'
b1 %
b1100101 !
#204000
0#
b0 7
03
b10 1
b1010 $
0'
b10 %
b1100110 !
#206000
1#
b1 7
13
b11 1
b11011 $
1'
b11 %
b1100111 !
#208000
0#
b0 7
03
b0 1
0'
b1000 $
0*
b0 %
b10 (
b1101000 !
#210000
1#
b1 7
13
b1 1
b11001 $
1'
b1 %
b1101001 !
#212000
0#
b0 7
03
b0 1
b1000 $
0'
b10 %
b1101010 !
#214000
1#
b1 7
13
b1 1
b11001 $
1'
b11 %
b1101011 !
#216000
0#
b0 7
03
b10 1
0'
b1010 $
1*
b0 %
b11 (
b1101100 !
#218000
1#
b1 7
13
b11 1
b11011 $
1'
b1 %
b1101101 !
#220000
0#
b0 7
03
b10 1
b1010 $
0'
b10 %
b1101110 !
#222000
1#
b1 7
13
b11 1
b11011 $
1'
b11 %
b1101111 !
#224000
0#
b10 7
03
16
b0 1
b11 4
0'
0*
b101100 $
1-
b0 %
b0 (
b11 +
b1110000 !
#226000
1#
b11 7
13
b1 1
b111101 $
1'
b1 %
b1110001 !
#228000
0#
b10 7
03
b0 1
b101100 $
0'
b10 %
b1110010 !
#230000
1#
b11 7
13
b1 1
b111101 $
1'
b11 %
b1110011 !
#232000
0#
b10 7
03
b10 1
0'
b101110 $
1*
b0 %
b1 (
b1110100 !
#234000
1#
b11 7
13
b11 1
b111111 $
1'
b1 %
b1110101 !
#236000
0#
b10 7
03
b10 1
b101110 $
0'
b10 %
b1110110 !
#238000
1#
b11 7
13
b11 1
b111111 $
1'
b11 %
b1110111 !
#240000
0#
b10 7
03
b0 1
0'
b101100 $
0*
b0 %
b10 (
b1111000 !
#242000
1#
b11 7
13
b1 1
b111101 $
1'
b1 %
b1111001 !
#244000
0#
b10 7
03
b0 1
b101100 $
0'
b10 %
b1111010 !
#246000
1#
b11 7
13
b1 1
b111101 $
1'
b11 %
b1111011 !
#248000
0#
b10 7
03
b10 1
0'
b101110 $
1*
b0 %
b11 (
b1111100 !
#250000
1#
b11 7
13
b11 1
b111111 $
1'
b1 %
b1111101 !
#252000
0#
b10 7
03
b10 1
b101110 $
0'
b10 %
b1111110 !
#254000
1#
b11 7
13
b11 1
b111111 $
1'
b11 %
b1111111 !
#256000
0#
b0 7
03
06
b0 1
b0 4
0'
0*
0-
b0 $
00
b0 %
b0 (
b0 +
b10 .
b10000000 !
#258000
1#
b1 7
13
b1 1
b10001 $
1'
b1 %
b10000001 !
#260000
0#
b0 7
03
b0 1
b0 $
0'
b10 %
b10000010 !
#262000
1#
b1 7
13
b1 1
b10001 $
1'
b11 %
b10000011 !
#264000
0#
b0 7
03
b10 1
0'
b10 $
1*
b0 %
b1 (
b10000100 !
#266000
1#
b1 7
13
b11 1
b10011 $
1'
b1 %
b10000101 !
#268000
0#
b0 7
03
b10 1
b10 $
0'
b10 %
b10000110 !
#270000
1#
b1 7
13
b11 1
b10011 $
1'
b11 %
b10000111 !
#272000
0#
b0 7
03
b0 1
0'
b0 $
0*
b0 %
b10 (
b10001000 !
#274000
1#
b1 7
13
b1 1
b10001 $
1'
b1 %
b10001001 !
#276000
0#
b0 7
03
b0 1
b0 $
0'
b10 %
b10001010 !
#278000
1#
b1 7
13
b1 1
b10001 $
1'
b11 %
b10001011 !
#280000
0#
b0 7
03
b10 1
0'
b10 $
1*
b0 %
b11 (
b10001100 !
#282000
1#
b1 7
13
b11 1
b10011 $
1'
b1 %
b10001101 !
#284000
0#
b0 7
03
b10 1
b10 $
0'
b10 %
b10001110 !
#286000
1#
b1 7
13
b11 1
b10011 $
1'
b11 %
b10001111 !
#288000
0#
b10 7
03
16
b0 1
b1 4
0'
0*
b100100 $
1-
b0 %
b0 (
b1 +
b10010000 !
#290000
1#
b11 7
13
b1 1
b110101 $
1'
b1 %
b10010001 !
#292000
0#
b10 7
03
b0 1
b100100 $
0'
b10 %
b10010010 !
#294000
1#
b11 7
13
b1 1
b110101 $
1'
b11 %
b10010011 !
#296000
0#
b10 7
03
b10 1
0'
b100110 $
1*
b0 %
b1 (
b10010100 !
#298000
1#
b11 7
13
b11 1
b110111 $
1'
b1 %
b10010101 !
#300000
0#
b10 7
03
b10 1
b100110 $
0'
b10 %
b10010110 !
#302000
1#
b11 7
13
b11 1
b110111 $
1'
b11 %
b10010111 !
#304000
0#
b10 7
03
b0 1
0'
b100100 $
0*
b0 %
b10 (
b10011000 !
#306000
1#
b11 7
13
b1 1
b110101 $
1'
b1 %
b10011001 !
#308000
0#
b10 7
03
b0 1
b100100 $
0'
b10 %
b10011010 !
#310000
1#
b11 7
13
b1 1
b110101 $
1'
b11 %
b10011011 !
#312000
0#
b10 7
03
b10 1
0'
b100110 $
1*
b0 %
b11 (
b10011100 !
#314000
1#
b11 7
13
b11 1
b110111 $
1'
b1 %
b10011101 !
#316000
0#
b10 7
03
b10 1
b100110 $
0'
b10 %
b10011110 !
#318000
1#
b11 7
13
b11 1
b110111 $
1'
b11 %
b10011111 !
#320000
0#
b0 7
03
06
b0 1
b0 4
0'
0*
b0 $
0-
b0 %
b0 (
b10 +
b10100000 !
#322000
1#
b1 7
13
b1 1
b10001 $
1'
b1 %
b10100001 !
#324000
0#
b0 7
03
b0 1
b0 $
0'
b10 %
b10100010 !
#326000
1#
b1 7
13
b1 1
b10001 $
1'
b11 %
b10100011 !
#328000
0#
b0 7
03
b10 1
0'
b10 $
1*
b0 %
b1 (
b10100100 !
#330000
1#
b1 7
13
b11 1
b10011 $
1'
b1 %
b10100101 !
#332000
0#
b0 7
03
b10 1
b10 $
0'
b10 %
b10100110 !
#334000
1#
b1 7
13
b11 1
b10011 $
1'
b11 %
b10100111 !
#336000
0#
b0 7
03
b0 1
0'
b0 $
0*
b0 %
b10 (
b10101000 !
#338000
1#
b1 7
13
b1 1
b10001 $
1'
b1 %
b10101001 !
#340000
0#
b0 7
03
b0 1
b0 $
0'
b10 %
b10101010 !
#342000
1#
b1 7
13
b1 1
b10001 $
1'
b11 %
b10101011 !
#344000
0#
b0 7
03
b10 1
0'
b10 $
1*
b0 %
b11 (
b10101100 !
#346000
1#
b1 7
13
b11 1
b10011 $
1'
b1 %
b10101101 !
#348000
0#
b0 7
03
b10 1
b10 $
0'
b10 %
b10101110 !
#350000
1#
b1 7
13
b11 1
b10011 $
1'
b11 %
b10101111 !
#352000
0#
b10 7
03
16
b0 1
b1 4
0'
0*
b100100 $
1-
b0 %
b0 (
b11 +
b10110000 !
#354000
1#
b11 7
13
b1 1
b110101 $
1'
b1 %
b10110001 !
#356000
0#
b10 7
03
b0 1
b100100 $
0'
b10 %
b10110010 !
#358000
1#
b11 7
13
b1 1
b110101 $
1'
b11 %
b10110011 !
#360000
0#
b10 7
03
b10 1
0'
b100110 $
1*
b0 %
b1 (
b10110100 !
#362000
1#
b11 7
13
b11 1
b110111 $
1'
b1 %
b10110101 !
#364000
0#
b10 7
03
b10 1
b100110 $
0'
b10 %
b10110110 !
#366000
1#
b11 7
13
b11 1
b110111 $
1'
b11 %
b10110111 !
#368000
0#
b10 7
03
b0 1
0'
b100100 $
0*
b0 %
b10 (
b10111000 !
#370000
1#
b11 7
13
b1 1
b110101 $
1'
b1 %
b10111001 !
#372000
0#
b10 7
03
b0 1
b100100 $
0'
b10 %
b10111010 !
#374000
1#
b11 7
13
b1 1
b110101 $
1'
b11 %
b10111011 !
#376000
0#
b10 7
03
b10 1
0'
b100110 $
1*
b0 %
b11 (
b10111100 !
#378000
1#
b11 7
13
b11 1
b110111 $
1'
b1 %
b10111101 !
#380000
0#
b10 7
03
b10 1
b100110 $
0'
b10 %
b10111110 !
#382000
1#
b11 7
13
b11 1
b110111 $
1'
b11 %
b10111111 !
#384000
0#
b0 7
03
06
b0 1
b10 4
0'
0*
0-
b1000 $
10
b0 %
b0 (
b0 +
b11 .
b11000000 !
#386000
1#
b1 7
13
b1 1
b11001 $
1'
b1 %
b11000001 !
#388000
0#
b0 7
03
b0 1
b1000 $
0'
b10 %
b11000010 !
#390000
1#
b1 7
13
b1 1
b11001 $
1'
b11 %
b11000011 !
#392000
0#
b0 7
03
b10 1
0'
b1010 $
1*
b0 %
b1 (
b11000100 !
#394000
1#
b1 7
13
b11 1
b11011 $
1'
b1 %
b11000101 !
#396000
0#
b0 7
03
b10 1
b1010 $
0'
b10 %
b11000110 !
#398000
1#
b1 7
13
b11 1
b11011 $
1'
b11 %
b11000111 !
#400000
0#
b0 7
03
b0 1
0'
b1000 $
0*
b0 %
b10 (
b11001000 !
#402000
1#
b1 7
13
b1 1
b11001 $
1'
b1 %
b11001001 !
#404000
0#
b0 7
03
b0 1
b1000 $
0'
b10 %
b11001010 !
#406000
1#
b1 7
13
b1 1
b11001 $
1'
b11 %
b11001011 !
#408000
0#
b0 7
03
b10 1
0'
b1010 $
1*
b0 %
b11 (
b11001100 !
#410000
1#
b1 7
13
b11 1
b11011 $
1'
b1 %
b11001101 !
#412000
0#
b0 7
03
b10 1
b1010 $
0'
b10 %
b11001110 !
#414000
1#
b1 7
13
b11 1
b11011 $
1'
b11 %
b11001111 !
#416000
0#
b10 7
03
16
b0 1
b11 4
0'
0*
b101100 $
1-
b0 %
b0 (
b1 +
b11010000 !
#418000
1#
b11 7
13
b1 1
b111101 $
1'
b1 %
b11010001 !
#420000
0#
b10 7
03
b0 1
b101100 $
0'
b10 %
b11010010 !
#422000
1#
b11 7
13
b1 1
b111101 $
1'
b11 %
b11010011 !
#424000
0#
b10 7
03
b10 1
0'
b101110 $
1*
b0 %
b1 (
b11010100 !
#426000
1#
b11 7
13
b11 1
b111111 $
1'
b1 %
b11010101 !
#428000
0#
b10 7
03
b10 1
b101110 $
0'
b10 %
b11010110 !
#430000
1#
b11 7
13
b11 1
b111111 $
1'
b11 %
b11010111 !
#432000
0#
b10 7
03
b0 1
0'
b101100 $
0*
b0 %
b10 (
b11011000 !
#434000
1#
b11 7
13
b1 1
b111101 $
1'
b1 %
b11011001 !
#436000
0#
b10 7
03
b0 1
b101100 $
0'
b10 %
b11011010 !
#438000
1#
b11 7
13
b1 1
b111101 $
1'
b11 %
b11011011 !
#440000
0#
b10 7
03
b10 1
0'
b101110 $
1*
b0 %
b11 (
b11011100 !
#442000
1#
b11 7
13
b11 1
b111111 $
1'
b1 %
b11011101 !
#444000
0#
b10 7
03
b10 1
b101110 $
0'
b10 %
b11011110 !
#446000
1#
b11 7
13
b11 1
b111111 $
1'
b11 %
b11011111 !
#448000
0#
b0 7
03
06
b0 1
b10 4
0'
0*
b1000 $
0-
b0 %
b0 (
b10 +
b11100000 !
#450000
1#
b1 7
13
b1 1
b11001 $
1'
b1 %
b11100001 !
#452000
0#
b0 7
03
b0 1
b1000 $
0'
b10 %
b11100010 !
#454000
1#
b1 7
13
b1 1
b11001 $
1'
b11 %
b11100011 !
#456000
0#
b0 7
03
b10 1
0'
b1010 $
1*
b0 %
b1 (
b11100100 !
#458000
1#
b1 7
13
b11 1
b11011 $
1'
b1 %
b11100101 !
#460000
0#
b0 7
03
b10 1
b1010 $
0'
b10 %
b11100110 !
#462000
1#
b1 7
13
b11 1
b11011 $
1'
b11 %
b11100111 !
#464000
0#
b0 7
03
b0 1
0'
b1000 $
0*
b0 %
b10 (
b11101000 !
#466000
1#
b1 7
13
b1 1
b11001 $
1'
b1 %
b11101001 !
#468000
0#
b0 7
03
b0 1
b1000 $
0'
b10 %
b11101010 !
#470000
1#
b1 7
13
b1 1
b11001 $
1'
b11 %
b11101011 !
#472000
0#
b0 7
03
b10 1
0'
b1010 $
1*
b0 %
b11 (
b11101100 !
#474000
1#
b1 7
13
b11 1
b11011 $
1'
b1 %
b11101101 !
#476000
0#
b0 7
03
b10 1
b1010 $
0'
b10 %
b11101110 !
#478000
1#
b1 7
13
b11 1
b11011 $
1'
b11 %
b11101111 !
#480000
0#
b10 7
03
16
b0 1
b11 4
0'
0*
b101100 $
1-
b0 %
b0 (
b11 +
b11110000 !
#482000
1#
b11 7
13
b1 1
b111101 $
1'
b1 %
b11110001 !
#484000
0#
b10 7
03
b0 1
b101100 $
0'
b10 %
b11110010 !
#486000
1#
b11 7
13
b1 1
b111101 $
1'
b11 %
b11110011 !
#488000
0#
b10 7
03
b10 1
0'
b101110 $
1*
b0 %
b1 (
b11110100 !
#490000
1#
b11 7
13
b11 1
b111111 $
1'
b1 %
b11110101 !
#492000
0#
b10 7
03
b10 1
b101110 $
0'
b10 %
b11110110 !
#494000
1#
b11 7
13
b11 1
b111111 $
1'
b11 %
b11110111 !
#496000
0#
b10 7
03
b0 1
0'
b101100 $
0*
b0 %
b10 (
b11111000 !
#498000
1#
b11 7
13
b1 1
b111101 $
1'
b1 %
b11111001 !
#500000
0#
b10 7
03
b0 1
b101100 $
0'
b10 %
b11111010 !
#502000
1#
b11 7
13
b1 1
b111101 $
1'
b11 %
b11111011 !
#504000
0#
b10 7
03
b10 1
0'
b101110 $
1*
b0 %
b11 (
b11111100 !
#506000
1#
b11 7
13
b11 1
b111111 $
1'
b1 %
b11111101 !
#508000
0#
b10 7
03
b10 1
b101110 $
0'
b10 %
b11111110 !
#510000
1#
b11 7
13
b11 1
b111111 $
1'
b11 %
b11111111 !
#512000
0#
b0 7
03
06
b0 1
b0 4
0'
0*
0-
b0 $
00
b0 %
b0 (
b0 +
b0 .
1&
1)
1,
1/
b0 !
b1 "
#514000
b1 %
b1 !
#516000
1#
b1 7
13
b1 1
b10001 $
1'
b10 %
b10 !
#518000
b11 %
b11 !
#520000
0#
b0 7
03
b0 1
b0 $
0'
b0 %
b1 (
b100 !
#522000
b1 %
b101 !
#524000
1#
b1 7
13
b1 1
b10001 $
1'
b10 %
b110 !
#526000
b11 %
b111 !
#528000
0#
b0 7
03
b10 1
0'
b10 $
1*
b0 %
b10 (
b1000 !
#530000
b1 %
b1001 !
#532000
1#
b1 7
13
b11 1
b10011 $
1'
b10 %
b1010 !
#534000
b11 %
b1011 !
#536000
0#
b0 7
03
b10 1
b10 $
0'
b0 %
b11 (
b1100 !
#538000
b1 %
b1101 !
#540000
1#
b1 7
13
b11 1
b10011 $
1'
b10 %
b1110 !
#542000
b11 %
b1111 !
#544000
0#
b0 7
03
b0 1
0'
b0 $
0*
b0 %
b0 (
b1 +
b10000 !
#546000
b1 %
b10001 !
#548000
1#
b1 7
13
b1 1
b10001 $
1'
b10 %
b10010 !
#550000
b11 %
b10011 !
#552000
0#
b0 7
03
b0 1
b0 $
0'
b0 %
b1 (
b10100 !
#554000
b1 %
b10101 !
#556000
1#
b1 7
13
b1 1
b10001 $
1'
b10 %
b10110 !
#558000
b11 %
b10111 !
#560000
0#
b0 7
03
b10 1
0'
b10 $
1*
b0 %
b10 (
b11000 !
#562000
b1 %
b11001 !
#564000
1#
b1 7
13
b11 1
b10011 $
1'
b10 %
b11010 !
#566000
b11 %
b11011 !
#568000
0#
b0 7
03
b10 1
b10 $
0'
b0 %
b11 (
b11100 !
#570000
b1 %
b11101 !
#572000
1#
b1 7
13
b11 1
b10011 $
1'
b10 %
b11110 !
#574000
b11 %
b11111 !
#576000
0#
b10 7
03
16
b0 1
b1 4
0'
0*
b100100 $
1-
b0 %
b0 (
b10 +
b100000 !
#578000
b1 %
b100001 !
#580000
1#
b11 7
13
b1 1
b110101 $
1'
b10 %
b100010 !
#582000
b11 %
b100011 !
#584000
0#
b10 7
03
b0 1
b100100 $
0'
b0 %
b1 (
b100100 !
#586000
b1 %
b100101 !
#588000
1#
b11 7
13
b1 1
b110101 $
1'
b10 %
b100110 !
#590000
b11 %
b100111 !
#592000
0#
b10 7
03
b10 1
0'
b100110 $
1*
b0 %
b10 (
b101000 !
#594000
b1 %
b101001 !
#596000
1#
b11 7
13
b11 1
b110111 $
1'
b10 %
b101010 !
#598000
b11 %
b101011 !
#600000
0#
b10 7
03
b10 1
b100110 $
0'
b0 %
b11 (
b101100 !
#602000
b1 %
b101101 !
#604000
1#
b11 7
13
b11 1
b110111 $
1'
b10 %
b101110 !
#606000
b11 %
b101111 !
#608000
0#
b10 7
03
b0 1
0'
b100100 $
0*
b0 %
b0 (
b11 +
b110000 !
#610000
b1 %
b110001 !
#612000
1#
b11 7
13
b1 1
b110101 $
1'
b10 %
b110010 !
#614000
b11 %
b110011 !
#616000
0#
b10 7
03
b0 1
b100100 $
0'
b0 %
b1 (
b110100 !
#618000
b1 %
b110101 !
#620000
1#
b11 7
13
b1 1
b110101 $
1'
b10 %
b110110 !
#622000
b11 %
b110111 !
#624000
0#
b10 7
03
b10 1
0'
b100110 $
1*
b0 %
b10 (
b111000 !
#626000
b1 %
b111001 !
#628000
1#
b11 7
13
b11 1
b110111 $
1'
b10 %
b111010 !
#630000
b11 %
b111011 !
#632000
0#
b10 7
03
b10 1
b100110 $
0'
b0 %
b11 (
b111100 !
#634000
b1 %
b111101 !
#636000
1#
b11 7
13
b11 1
b110111 $
1'
b10 %
b111110 !
#638000
b11 %
b111111 !
#640000
0#
b0 7
03
06
b0 1
b0 4
0'
0*
b0 $
0-
b0 %
b0 (
b0 +
b1 .
b1000000 !
#642000
b1 %
b1000001 !
#644000
1#
b1 7
13
b1 1
b10001 $
1'
b10 %
b1000010 !
#646000
b11 %
b1000011 !
#648000
0#
b0 7
03
b0 1
b0 $
0'
b0 %
b1 (
b1000100 !
#650000
b1 %
b1000101 !
#652000
1#
b1 7
13
b1 1
b10001 $
1'
b10 %
b1000110 !
#654000
b11 %
b1000111 !
#656000
0#
b0 7
03
b10 1
0'
b10 $
1*
b0 %
b10 (
b1001000 !
#658000
b1 %
b1001001 !
#660000
1#
b1 7
13
b11 1
b10011 $
1'
b10 %
b1001010 !
#662000
b11 %
b1001011 !
#664000
0#
b0 7
03
b10 1
b10 $
0'
b0 %
b11 (
b1001100 !
#666000
b1 %
b1001101 !
#668000
1#
b1 7
13
b11 1
b10011 $
1'
b10 %
b1001110 !
#670000
b11 %
b1001111 !
#672000
0#
b0 7
03
b0 1
0'
b0 $
0*
b0 %
b0 (
b1 +
b1010000 !
#674000
b1 %
b1010001 !
#676000
1#
b1 7
13
b1 1
b10001 $
1'
b10 %
b1010010 !
#678000
b11 %
b1010011 !
#680000
0#
b0 7
03
b0 1
b0 $
0'
b0 %
b1 (
b1010100 !
#682000
b1 %
b1010101 !
#684000
1#
b1 7
13
b1 1
b10001 $
1'
b10 %
b1010110 !
#686000
b11 %
b1010111 !
#688000
0#
b0 7
03
b10 1
0'
b10 $
1*
b0 %
b10 (
b1011000 !
#690000
b1 %
b1011001 !
