8x3_encoder/design.sv
`timescale 1ns/1ps
module encoder_8x3 (
  input  [7:0] in,
  output reg [2:0] out
);

  always @(*) begin
    casex (in)
      8'b00000001: out = 3'b000;
      8'b00000010: out = 3'b001;
      8'b00000100: out = 3'b010;
      8'b00001000: out = 3'b011;
      8'b00010000: out = 3'b100;
      8'b00100000: out = 3'b101;
      8'b01000000: out = 3'b110;
      8'b10000000: out = 3'b111;
      default:     out = 3'bxxx;
    endcase
  end

endmodule

8x3_encoder/testbench.sv
`timescale 1ns/1ps
module tb_encoder_8x3();

  reg  [7:0] in;
  wire [2:0] out;
  integer i;

  encoder_8x3 uut (.in(in), .out(out));

  initial begin
    $dumpfile("tb_encoder_8x3.vcd");
    $dumpvars(0, uut);
  end

  initial begin
    in = 8'b00000000;
    #2;
    for (i = 0; i < 8; i = i + 1) begin
      in = 8'b1 << i;
      #2;
    end
  end

  initial begin
    $monitor("time=%g | in=%b | out=%b", $time, in, out);
    #20 $finish;
  end

endmodule

8x3_encoder/tb_encoder_8x3.vcd
$date
	Fri Aug 22 15:25:28 2025
$end
$version
	Icarus Verilog
$end
$timescale
	1ps
$end
$scope module tb_encoder_8x3 $end
$scope module uut $end
$var wire 8 ! in [7:0] $end
$var reg 3 " out [2:0] $end
$upscope $end
$upscope $end
$enddefinitions $end
$comment Show the parameter values. $end
$dumpall
$end
#0
$dumpvars
bx "
b0 !
$end
#2000
b0 "
b1 !
#4000
b1 "
b10 !
#6000
b10 "
b100 !
#8000
b11 "
b1000 !
#10000
b100 "
b10000 !
#12000
b101 "
b100000 !
#14000
b110 "
b1000000 !
#16000
b111 "
b10000000 !
