full_adder_using_half_adder/design.sv
module half_adder (
  input a, b,
  output sum, carry
);
  assign sum = a ^ b;
  assign carry = a & b;
endmodule

module full_adder (
  input a, b, cin,
  output sum, cout
);
  wire s1, c1, c2;

  half_adder HA1 (a, b, s1, c1);
  half_adder HA2 (s1, cin, sum, c2);
  or(cout,c1,c2);
endmodule

full_adder_using_half_adder/testbench.sv
`timescale 1ns/1ps
module tb_full_adder;
  reg a, b, c;
  wire sum, cout;

  full_adder uut (
    .a(a),
    .b(b),
    .cin(c),
    .sum(sum),
    .cout(cout)
  );

  initial begin
    a = 0; b = 0; c = 0;
    $dumpfile("tb_full_adder.vcd");
    $dumpvars(0, uut);
  end

  always #4 a = a + 1'b1;
  always #2 b = b + 1'b1;
  always #1 c = c + 1'b1;

  initial  $monitor("%b %b %b | %b %b", a, b, c, sum, cout);
  initial #8 $finish;   // <-- only 8 rows now
endmodule

full_adder_using_half_adder/tb_full_adder.vcd
$date
	Thu Aug 21 15:01:57 2025
$end
$version
	Icarus Verilog
$end
$timescale
	1ps
$end
$scope module tb_full_adder $end
$scope module uut $end
$var wire 1 ! a $end
$var wire 1 " b $end
$var wire 1 # cin $end
$var wire 1 $ cout $end
$var wire 1 % sum $end
$var wire 1 & s1 $end
$var wire 1 ' c2 $end
$var wire 1 ( c1 $end
$scope module HA1 $end
$var wire 1 ! a $end
$var wire 1 " b $end
$var wire 1 ( carry $end
$var wire 1 & sum $end
$upscope $end
$scope module HA2 $end
$var wire 1 & a $end
$var wire 1 # b $end
$var wire 1 ' carry $end
$var wire 1 % sum $end
$upscope $end
$upscope $end
$upscope $end
$enddefinitions $end
$comment Show the parameter values. $end
$dumpall
$end
#0
$dumpvars
0(
0'
0&
0%
0$
0#
0"
0!
$end
#1000
1%
1#
#2000
1&
0#
1"
#3000
1$
0%
1'
1#
#4000
0$
1%
0'
0#
0"
1!
#5000
1$
0%
1'
1#
#6000
0'
0&
1(
0#
1"
#7000
1%
1#
#8000
0$
0%
0(
0#
0"
0!
