t_flipflop/design.sv
`timescale 1ns/1ps
module t_ff(output reg q,qbar,input t,clk,clear);
  always @ (posedge clk  or negedge clear)
    if(!clear)
      begin
        q<=1'b0;
        qbar<=1'b1;
      end
  else 
    begin
      casex(t)
      1'b0:begin q<=q;qbar<=qbar; end
      1'b1:begin q<=~q;qbar<=~qbar; end
      default: {q,qbar} <= 2'bxx;
    endcase
    end
endmodule

t_flipflop/testbench.sv
`timescale 1ns/1ps
module tb_t_ff;
  reg t,clk,clear;
  wire q,qbar;
  
  t_ff uut(.t(t),.qbar(qbar),.q(q),.clk(clk),.clear(clear));
  
  initial
    begin
      clk=1'b0;
      forever #5 clk=~clk;
    end
  initial
    begin
      t=1'b0;
       clear = 1'b0;    // start with reset active
    #5 clear = 1'b1; // release reset before first posedge clk
      $dumpfile("tb_t_ff.vcd");
    	$dumpvars(0, uut);
    end
  always #10 t=~t;
  initial
    begin
      $monitor("time=%g,t=%b,clk=%b,clear=%b,q=%b,qbar=%b",$time,t,clk,clear,q,qbar);
  #100 $finish;
    end
endmodule

t_flipflop/tb_t_ff.vcd
$date
	Thu Aug 21 17:53:57 2025
$end
$version
	Icarus Verilog
$end
$timescale
	1ps
$end
$scope module tb_t_ff $end
$scope module uut $end
$var wire 1 ! clear $end
$var wire 1 " clk $end
$var wire 1 # t $end
$var reg 1 $ q $end
$var reg 1 % qbar $end
$upscope $end
$upscope $end
$enddefinitions $end
$comment Show the parameter values. $end
$dumpall
$end
#5000
$dumpvars
1%
0$
0#
1"
1!
$end
#10000
0"
1#
#15000
0%
1$
1"
#20000
0"
0#
#25000
1"
#30000
0"
1#
#35000
1%
0$
1"
#40000
0"
0#
#45000
1"
#50000
0"
1#
#55000
0%
1$
1"
#60000
0"
0#
#65000
1"
#70000
0"
1#
#75000
1%
0$
1"
#80000
0"
0#
#85000
1"
#90000
0"
1#
#95000
0%
1$
1"
#100000
0"
0#
