piso/design.sv
`timescale 1ns/1ps
module piso(v,clk,sel,clr,d);
  reg [3:0] q;
  input [3:0]d;
  input sel,clk,clr;
  output reg v;
  always @ (posedge clk)
    if(clr==1)
      q<=4'b0000;
  else if(sel==0)
    q<=d;
  else
    begin
      v<=q[0];
      q<=q>>1;
    end
endmodule

piso/testbench.sv
`timescale 1ns/1ps
module tb_piso;

    reg clk, sel, clr;
    reg [3:0] d;
    wire v;

    piso uut(
        .clk(clk),
        .sel(sel),
        .clr(clr),
        .d(d),
        .v(v)
    );

    initial begin
        clk = 0;
        forever #5 clk = ~clk;
    end

    initial begin
        $dumpfile("tb_piso.vcd");
        $dumpvars(0, uut);
    end

    initial begin
        clr = 1; sel = 0; d = 4'b1011;  
        #10 clr = 0;                     

        #10 sel = 1;                      
        #40;                              

        sel = 0; d = 4'b1100;             
        #10 sel = 1;                      
        #40;                              

        $finish;
    end

    initial begin
        $monitor("time=%0t | clr=%b sel=%b d=%b v=%b q=%b", 
                  $time, clr, sel, d, v, uut.q);
    end

endmodule

piso/tb_piso.vcd
$date
	Fri Aug 22 17:03:52 2025
$end
$version
	Icarus Verilog
$end
$timescale
	1ps
$end
$scope module tb_piso $end
$scope module uut $end
$var wire 1 ! clk $end
$var wire 1 " clr $end
$var wire 4 # d [3:0] $end
$var wire 1 $ sel $end
$var reg 4 % q [3:0] $end
$var reg 1 & v $end
$upscope $end
$upscope $end
$enddefinitions $end
$comment Show the parameter values. $end
$dumpall
$end
#0
$dumpvars
x&
bx %
0$
b1011 #
1"
0!
$end
#5000
b0 %
1!
#10000
0!
0"
#15000
b1011 %
1!
#20000
0!
1$
#25000
b101 %
1&
1!
#30000
0!
#35000
b10 %
1!
#40000
0!
#45000
b1 %
0&
1!
#50000
0!
#55000
b0 %
1&
1!
#60000
0!
b1100 #
0$
#65000
b1100 %
1!
#70000
0!
1$
#75000
b110 %
0&
1!
#80000
0!
#85000
b11 %
1!
#90000
0!
#95000
b1 %
1&
1!
#100000
0!
#105000
b0 %
1!
