full_adder/design.sv
// Code your design here
`timescale 10ns/1ns 
module str(s,co,a,b,c); 
  input a,b,c; 
  output reg s,co; 
  always @(*)
    begin 
      s=a^b^c;
      co=a&b|(c&(a^b));
    end
  
endmodule

full_adder/testbench.sv
`timescale 10ns/1ns
module tb_str;
  reg a, b, c;      // Inputs
  wire s, co;       // Outputs

  // Instantiate the full adder
  str uut (
    .s(s),
    .co(co),
    .a(a),
    .b(b),
    .c(c)
  );

  initial begin
    $dumpfile("tb_str.vcd");
    $dumpvars(0, uut);  // dump DUT only (no duplicates)

    $display("a b c | s co | Expected s co");
    $display("----------------------------");

    // Apply all 8 input combinations
    a=0; b=0; c=0; #10;
    $display("%b %b %b | %b %b |    0 0", a, b, c, s, co);

    a=0; b=0; c=1; #10;
    $display("%b %b %b | %b %b |    1 0", a, b, c, s, co);

    a=0; b=1; c=0; #10;
    $display("%b %b %b | %b %b |    1 0", a, b, c, s, co);

    a=0; b=1; c=1; #10;
    $display("%b %b %b | %b %b |    0 1", a, b, c, s, co);

    a=1; b=0; c=0; #10;
    $display("%b %b %b | %b %b |    1 0", a, b, c, s, co);

    a=1; b=0; c=1; #10;
    $display("%b %b %b | %b %b |    0 1", a, b, c, s, co);

    a=1; b=1; c=0; #10;
    $display("%b %b %b | %b %b |    0 1", a, b, c, s, co);

    a=1; b=1; c=1; #10;
    $display("%b %b %b | %b %b |    1 1", a, b, c, s, co);

    $finish;
  end
endmodule

full_adder/tb_str.vcd
$date
	Thu Aug 21 14:16:12 2025
$end
$version
	Icarus Verilog
$end
$timescale
	1ns
$end
$scope module tb_str $end
$scope module uut $end
$var wire 1 ! a $end
$var wire 1 " b $end
$var wire 1 # c $end
$var reg 1 $ co $end
$var reg 1 % s $end
$upscope $end
$upscope $end
$enddefinitions $end
$comment Show the parameter values. $end
$dumpall
$end
#0
$dumpvars
0%
0$
0#
0"
0!
$end
#100
1%
1#
#200
0#
1"
#300
1$
0%
1#
#400
0$
1%
0#
0"
1!
#500
1$
0%
1#
#600
0#
1"
#700
1%
1#
